{
  "$schema": "https://developer.microsoft.com/json-schemas/fabric/item/report/definition/visualContainer/2.1.0/schema.json",
  "name": "97785175ac754067a197",
  "position": {
    "x": 21.428571428571431,
    "y": 418.5714285714285,
    "z": 19000,
    "height": 280,
    "width": 307.14285714285717,
    "tabOrder": 19000
  },
  "visual": {
    "visualType": "textbox",
    "objects": {
      "general": [
        {
          "properties": {
            "paragraphs": [
              {
                "textRuns": [
                  {
                    "value": ""
                  }
                ],
                "horizontalTextAlignment": "center"
              },
              {
                "textRuns": [
                  {
                    "value": ""
                  }
                ]
              },
              {
                "textRuns": [
                  {
                    "value": ""
                  }
                ]
              },
              {
                "textRuns": [
                  {
                    "value": "The Thai Chicken Pizza",
                    "textStyle": {
                      "fontWeight": "bold",
                      "fontSize": "16pt"
                    }
                  },
                  {
                    "value": " was the most sold pizza in terms of revenue.",
                    "textStyle": {
                      "fontSize": "16pt"
                    }
                  }
                ],
                "horizontalTextAlignment": "center"
              },
              {
                "textRuns": [
                  {
                    "value": ""
                  }
                ]
              },
              {
                "textRuns": [
                  {
                    "value": "While ",
                    "textStyle": {
                      "fontSize": "16pt"
                    }
                  },
                  {
                    "value": "The Classic Deluxe Pizza",
                    "textStyle": {
                      "fontWeight": "bold",
                      "fontSize": "16pt"
                    }
                  },
                  {
                    "value": " is the most selling by quantity and total orders sold.",
                    "textStyle": {
                      "fontSize": "16pt"
                    }
                  }
                ],
                "horizontalTextAlignment": "center"
              }
            ]
          }
        }
      ]
    },
    "visualContainerObjects": {
      "background": [
        {
          "properties": {
            "color": {
              "solid": {
                "color": {
                  "expr": {
                    "ThemeDataColor": {
                      "ColorId": 7,
                      "Percent": 0.6
                    }
                  }
                }
              }
            }
          }
        }
      ]
    },
    "drillFilterOtherVisuals": true
  }
}